dimsm/__about__.py
dimsm/__init__.py
dimsm/dimension.py
dimsm/measurement.py
dimsm/prior.py
dimsm/process.py
dimsm/smoother.py
dimsm/solver.py
dimsm-0.0.0.dist-info/LICENSE
dimsm-0.0.0.dist-info/METADATA
dimsm-0.0.0.dist-info/WHEEL
dimsm-0.0.0.dist-info/top_level.txt
dimsm-0.0.0.dist-info/RECORD
